fastapi_better_logger/__init__.py
fastapi_better_logger/py.typed
fastapi_better_logger/configs/__init__.py
fastapi_better_logger/configs/default_aws_config.py
fastapi_better_logger/configs/default_console_config.py
fastapi_better_logger/formatters/AwsAccessFormatter.py
fastapi_better_logger/formatters/AwsFormatter.py
fastapi_better_logger/formatters/ColoredAccessFormatter.py
fastapi_better_logger/formatters/ColoredFormatter.py
fastapi_better_logger/formatters/DefaultFormatter.py
fastapi_better_logger/formatters/__init__.py
fastapi_better_logger/handlers/AwsLogsHandler.py
fastapi_better_logger/handlers/__init__.py
fastapi_better_logger-0.0.5.data/data/LICENSE.md
fastapi_better_logger-0.0.5.dist-info/LICENSE.md
fastapi_better_logger-0.0.5.dist-info/METADATA
fastapi_better_logger-0.0.5.dist-info/WHEEL
fastapi_better_logger-0.0.5.dist-info/top_level.txt
fastapi_better_logger-0.0.5.dist-info/zip-safe
fastapi_better_logger-0.0.5.dist-info/RECORD
